addytool/__init__.py
addytool/endpoint.py
addytool/workflow.py
addytool-0.0.3.dist-info/LICENSE
addytool-0.0.3.dist-info/METADATA
addytool-0.0.3.dist-info/WHEEL
addytool-0.0.3.dist-info/top_level.txt
addytool-0.0.3.dist-info/RECORD
