Metadata-Version: 2.1
Name: addytool
Version: 0.0.3
Summary: A package for managing Addigy more intelligently.
Home-page: https://github.com/Addigy-Community/addytool
Author: Benjamin Morales
Author-email: bmorales@gocirrus.com
License: UNKNOWN
Platform: UNKNOWN
Classifier: Operating System :: MacOS :: MacOS X
Requires-Dist: requests
Requires-Dist: keyring
